README.md
setup.py
CellFreeGMF/DEG_fun.py
CellFreeGMF/R_script.py
CellFreeGMF/__init__.py
CellFreeGMF/config.py
CellFreeGMF/deconvolution.py
CellFreeGMF/diagnosis_ML.py
CellFreeGMF/utils.py
CellFreeGMF.egg-info/PKG-INFO
CellFreeGMF.egg-info/SOURCES.txt
CellFreeGMF.egg-info/dependency_links.txt
CellFreeGMF.egg-info/top_level.txt