Metadata-Version: 2.4
Name: CellFreeGMF
Version: 0.0.0
Summary: cfRNA
Author: Wenxiang Zhang
Author-email: 
Keywords: python,windows,mac,linux,cfRNA,CellFreeGMF
Classifier: Development Status :: 1 - Planning
Classifier: Intended Audience :: Developers
Classifier: Programming Language :: Python :: 3
Classifier: Operating System :: Unix
Classifier: Operating System :: MacOS :: MacOS X
Classifier: Operating System :: Microsoft :: Windows
Dynamic: author
Dynamic: classifier
Dynamic: description
Dynamic: description-content-type
Dynamic: keywords
Dynamic: summary
